TOPSIS_Ashmeet/102103742.py
TOPSIS_Ashmeetkaur_102103742-1.0.0.dist-info/LICENSE
TOPSIS_Ashmeetkaur_102103742-1.0.0.dist-info/METADATA
TOPSIS_Ashmeetkaur_102103742-1.0.0.dist-info/WHEEL
TOPSIS_Ashmeetkaur_102103742-1.0.0.dist-info/top_level.txt
TOPSIS_Ashmeetkaur_102103742-1.0.0.dist-info/RECORD
