Metadata-Version: 2.1
Name: TOPSIS-Ashmeetkaur-102103742
Version: 1.0.0
Summary: TOPSIS_Ashmeet
Home-page: https://github.com/Khushibansal15/Topsis-Implementation
Author: Ashmeet Kaur
Author-email: ash0207030@gmail.com
License: MIT
Classifier: License :: OSI Approved :: MIT License
Classifier: Programming Language :: Python :: 3.6
Classifier: Programming Language :: Python :: 3.7
Classifier: Programming Language :: Python :: 3.8
License-File: LICENSE
